bugsy/__init__.py
bugsy/attachment.py
bugsy/bug.py
bugsy/bugsy.py
bugsy/errors.py
bugsy/search.py
tests/__init__.py
tests/conftest.py
tests/test_attachment.py
tests/test_bugs.py
tests/test_bugsy.py
tests/test_errors.py
tests/test_search.py
bugsy-0.12.0.dist-info/LICENSE
bugsy-0.12.0.dist-info/METADATA
bugsy-0.12.0.dist-info/WHEEL
bugsy-0.12.0.dist-info/top_level.txt
bugsy-0.12.0.dist-info/RECORD
