Metadata-Version: 2.1
Name: bugsy
Version: 0.12.0
Summary: A library for interacting Bugzilla Native REST API
Home-page: https://github.com/AutomatedTester/Bugsy
Author: David Burns
Author-email: david.burns@theautomatedtester.co.uk
License: UNKNOWN
Platform: UNKNOWN
Classifier: Development Status :: 3 - Alpha
Classifier: Intended Audience :: Developers
Classifier: License :: OSI Approved :: Apache Software License
Classifier: Operating System :: POSIX
Classifier: Operating System :: Microsoft :: Windows
Classifier: Operating System :: MacOS :: MacOS X
Classifier: Topic :: Software Development :: Libraries
Classifier: Programming Language :: Python
Requires-Dist: requests (>=1.1.0)
